TwVideoManager/__init__.py
TwVideoManager/models.py
TwVideoManager-0.0.1b20190924.dist-info/LICENSE
TwVideoManager-0.0.1b20190924.dist-info/METADATA
TwVideoManager-0.0.1b20190924.dist-info/WHEEL
TwVideoManager-0.0.1b20190924.dist-info/top_level.txt
TwVideoManager-0.0.1b20190924.dist-info/RECORD
