Metadata-Version: 2.1
Name: TwVideoManager
Version: 0.0.1b20190924
Summary: Unified Twitch Video manager via Local and Google Drive
Home-page: https://github.com/R3turn-Dev/TwVideoManager/
Author: Eunhak Lee(return0927)
Author-email: admin@return0927.xyz
License: LGPL-3.0
Platform: UNKNOWN
Classifier: Programming Language :: Python :: 3
Classifier: License :: OSI Approved :: GNU Lesser General Public License v3 (LGPLv3)
Classifier: Operating System :: OS Independent
Requires-Python: >=3.7
